src/griddingmachine/__init__.py
python_griddingmachine-0.1.2.dist-info/LICENSE
python_griddingmachine-0.1.2.dist-info/WHEEL
python_griddingmachine-0.1.2.dist-info/METADATA
python_griddingmachine-0.1.2.dist-info/RECORD
