Metadata-Version: 2.1
Name: python-griddingmachine
Version: 0.1.2
Summary: GriddingMachine - a database and tool for earth system modeling
License: Apache-2.0
Author: Yujie Wang
Author-email: jesiner@gmail.com
Requires-Python: >=3.8,<4.0
Classifier: License :: OSI Approved :: Apache Software License
Classifier: Programming Language :: Python :: 3
Classifier: Programming Language :: Python :: 3.10
Classifier: Programming Language :: Python :: 3.8
Classifier: Programming Language :: Python :: 3.9
Requires-Dist: numpy (>=1.0,<2.0)
Requires-Dist: toml (>=0.10,<0.11)
